setup.py
C/__c.py
C/__init__.py
C_easy.egg-info/PKG-INFO
C_easy.egg-info/SOURCES.txt
C_easy.egg-info/dependency_links.txt
C_easy.egg-info/not-zip-safe
C_easy.egg-info/requires.txt
C_easy.egg-info/top_level.txt